odoo/addons/ssi_salesperson_mixin/README.rst
odoo/addons/ssi_salesperson_mixin/__init__.py
odoo/addons/ssi_salesperson_mixin/__manifest__.py
odoo/addons/ssi_salesperson_mixin/models/__init__.py
odoo/addons/ssi_salesperson_mixin/models/mixin_salesperson.py
odoo/addons/ssi_salesperson_mixin/static/description/icon.png
odoo14_addon_ssi_salesperson_mixin-14.0.1.1.0.dist-info/METADATA
odoo14_addon_ssi_salesperson_mixin-14.0.1.1.0.dist-info/WHEEL
odoo14_addon_ssi_salesperson_mixin-14.0.1.1.0.dist-info/top_level.txt
odoo14_addon_ssi_salesperson_mixin-14.0.1.1.0.dist-info/RECORD
